sptanalysis/__init__.py
sptanalysis/angles.py
sptanalysis/msd.py
sptanalysis/nnd.py
sptanalysis/utils/__init__.py
sptanalysis/utils/util_functions.py
sptanalysis/utils/converters/__init__.py
sptanalysis/utils/converters/amstracks.py
sptanalysis/utils/converters/smaug_nobias.py
sptanalysis-0.2.0.dist-info/METADATA
sptanalysis-0.2.0.dist-info/WHEEL
sptanalysis-0.2.0.dist-info/RECORD
