Metadata-Version: 2.4
Name: sptanalysis
Version: 0.2.0
Summary: Single Molecule Trajectory Analysis: With MSD and Angle Modules
Requires-Python: >=3.12
Requires-Dist: numpy>=2.2.1
Requires-Dist: scipy>=1.15.1
